Metadata-Version: 2.1
Name: single-variable-expression-parser-ALIEZZAT
Version: 0.0.1
Summary: A package for parsing mathmatical expressions
Home-page: https://github.com/AliEzzatOdeh/SingleVariableExpressionParser
Author: ALIEZZAT ODEH
Author-email: aliezzat1993@outlook.com
License: UNKNOWN
Platform: UNKNOWN
Classifier: Programming Language :: Python :: 3.6
Classifier: License :: OSI Approved :: MIT License
Classifier: Operating System :: OS Independent
Classifier: Intended Audience :: Developers
Classifier: Development Status :: 3 - Alpha
Requires-Python: >=3.6
